{
    "day": "12.03.2004",
    "time": "20:00",
    "type": "Soirée",
    "location": "Hamburg",
    "theater": "Theater Neue Flora",
    "cast": {
        "Graf von Krolock": [
            "Felix Martin"
        ],
        "Alfred": [
            "Fredrik Wickerts"
        ],
        "Professor Abronsius": [
            "Werner Bauer"
        ],
        "Sarah": [
            "Jessica Kessler"
        ],
        "Chagal": [
            "Jerzy Jeszke"
        ],
        "Magda": [
            "Femke Soetenga"
        ],
        "Rebecca": [
            "Jan Merchant"
        ],
        "Herbert": [
            "Norbert Kohler"
        ],
        "Koukol": [
            "Kai Helm"
        ],
        "Solotänzer": [
            "Wolf Bader",
            "Christopher Tölle",
            "Peter Horemans",
            "Jacquie Biggs"
        ],
        "Dirigent": [
            "Bernhard Volk"
        ]
    }
}