{
    "day": "23.05.2004",
    "time": "19:00",
    "type": "Soirée",
    "production": 3,
    "location": "Hamburg",
    "theater": "Theater Neue Flora",
    "cast": {
        "Graf von Krolock": [
            "Felix Martin"
        ],
        "Alfred": [
            "Fredrik Wickerts"
        ],
        "Professor Abronsius": [
            "Werner Bauer"
        ],
        "Sarah": [
            "Gabriella Mezöfi"
        ],
        "Chagal": [
            "Jerzy Jeszke"
        ],
        "Magda": [
            "Anna Thorén"
        ],
        "Rebecca": [
            "Jan Merchant"
        ],
        "Herbert": [
            "Norbert Kohler"
        ],
        "Koukol": [
            "Kai Helm"
        ],
        "Solotänzer": [
            "Peter Horemans",
            "Andrew Chadwick",
            "Robert Johansson",
            "Jacquie Biggs"
        ],
        "Dirigent": [
            "Bernhard Volk"
        ]
    }
}