{
    "day": "27.03.2004",
    "time": "15:00",
    "type": "Matinée",
    "production": 3,
    "location": "Hamburg",
    "theater": "Theater Neue Flora",
    "cast": {
        "Graf von Krolock": [
            "Felix Martin"
        ],
        "Alfred": [
            "Patrick Mares"
        ],
        "Professor Abronsius": [
            "Norbert Kohler"
        ],
        "Sarah": [
            "Jessica Kessler"
        ],
        "Chagal": [
            "Jerzy Jeszke"
        ],
        "Magda": [
            "Femke Soetenga"
        ],
        "Rebecca": [
            "Jan Merchant"
        ],
        "Herbert": [
            "Michel Driesse"
        ],
        "Koukol": [
            "Kai Helm"
        ],
        "Solotänzer": [
            "Wolf Bader",
            "Andrew Chadwick",
            "Robert Johansson",
            "Jacquie Biggs"
        ],
        "Dirigent": [
            "Bernhard Volk"
        ]
    }
}