{
    "day": "08.09.2001",
    "time": "20:00",
    "type": "Soirée",
    "production": 2,
    "location": "Stuttgart",
    "theater": "Apollo-Theater",
    "cast": {
        "Graf von Krolock": [
            "Kevin Tarte"
        ],
        "Alfred": [
            "Stefan Poslovski"
        ],
        "Professor Abronsius": [
            "Werner Bauer"
        ],
        "Sarah": [
            "Barbara Köhler"
        ],
        "Chagal": [
            "James Daniel Frost"
        ],
        "Magda": [
            "Debby Boekema"
        ],
        "Rebecca": [
            "Jeanne-Marie Nigl"
        ],
        "Herbert": [
            "Thomas Mülner"
        ],
        "Koukol": [
            "Kai Helm"
        ],
        "Solotänzer": [
            "David Hartland",
            "Stéphane Le Breton",
            "Marc Bollmeyer",
            "Margherita Huisman"
        ],
        "Dirigent": [
            "Adrian Werum"
        ]
    }
}