{
    "day": "22.12.2016",
    "time": "19:30",
    "type": "Soirée",
    "production": 10,
    "location": "München",
    "theater": "Deutsches Theater München",
    "cast": {
        "Dirigent": [
            "Leif Klinkhardt"
        ],
        "Graf von Krolock": [
            "Jan Ammann"
        ],
        "Sarah": [
            "Veronica Appeddu"
        ],
        "Alfred": [
            "Noah Wili"
        ],
        "Professor Abronsius": [
            "Victor Petersen"
        ],
        "Chagal": [
            "Nicolas Tenerani"
        ],
        "Magda": [
            "Merel Zeeman"
        ],
        "Herbert": [
            "Milan van Waardenburg"
        ],
        "Rebecca": [
            "Yvonne Köstler"
        ],
        "Koukol": [
            "Paolo Bianca"
        ],
        "Tanzsolisten": [
            "Kevin Schmid",
            "Joe Nolan",
            "Katie Allday"
        ],
        "Gesangssolisten": [
            "Sander van Wissen",
            "Kirill Zolygin"
        ],
        "Tanzensemble": [
            "David Baranya",
            "Stefan Mosonyi",
            "Nicola Trazzi",
            "Veronika Enders",
            "Samantha Harris-Hughes",
            "Vicki Douglas",
            "Nicole Ollio"
        ],
        "Gesangsensemble": [
            "Torsten Ankert",
            "Pascal Höwing",
            "Marina Maniglio",
            "Anja Wendzel",
            "Karolin Konert",
            "Astrid Gollob"
        ]
    }
}