{
    "day": "20.09.2016",
    "time": "19:30",
    "type": "Soirée",
    "location": "Berlin",
    "theater": "Theater des Westens",
    "cast": {
        "Dirigent": [
            "Robert Paul"
        ],
        "Graf von Krolock": [
            "Jan Ammann"
        ],
        "Sarah": [
            "Marina Maniglio"
        ],
        "Alfred": [
            "Tom van der Ven"
        ],
        "Professor Abronsius": [
            "Victor Petersen"
        ],
        "Chagal": [
            "Torsten Ankert"
        ],
        "Magda": [
            "Merel Zeeman"
        ],
        "Herbert": [
            "Sander van Wissen"
        ],
        "Rebecca": [
            "Pamela Zottele"
        ],
        "Koukol": [
            "Paolo Bianca"
        ],
        "Tanzsolisten": [
            "Kevin Schmid",
            "Máté Gyenei",
            "Astrid Gollob"
        ],
        "Gesangssolisten": [
            "Michael Anzalone",
            "Kirill Zolygin"
        ],
        "Tanzensemble": [
            "Joe Nolan",
            "Alex Hyne",
            "Nicola Trazzi",
            "Veronika Enders",
            "Katie Allday",
            "Vicki Douglas",
            "Nicole Ollio"
        ],
        "Gesangsensemble": [
            "Andrew Chadwick",
            "Thomas Höfner",
            "Pascal Höwing",
            "Noah Wili",
            "Anja Wendzel",
            "Karolin Konert",
            "Samantha Harris-Hughes",
            "Sanne Buskermolen"
        ]
    }
}